CHANGES.txt
README.txt
setup.cfg
setup.py
src/__init__.py
src/Products/__init__.py
src/Products.Gloworm.egg-info/PKG-INFO
src/Products.Gloworm.egg-info/SOURCES.txt
src/Products.Gloworm.egg-info/dependency_links.txt
src/Products.Gloworm.egg-info/entry_points.txt
src/Products.Gloworm.egg-info/namespace_packages.txt
src/Products.Gloworm.egg-info/not-zip-safe
src/Products.Gloworm.egg-info/requires.txt
src/Products.Gloworm.egg-info/top_level.txt
src/Products/Gloworm/__init__.py
src/Products/Gloworm/configure.zcml
src/Products/Gloworm/integration.py
src/Products/Gloworm/profiles.zcml
src/Products/Gloworm/Extensions/Install.py
src/Products/Gloworm/Extensions/__init__.py
src/Products/Gloworm/browser/__init__.py
src/Products/Gloworm/browser/configure.zcml
src/Products/Gloworm/browser/glowormHtmlHeadIncludes.pt
src/Products/Gloworm/browser/glowormInspectLink.pt
src/Products/Gloworm/browser/glowormPanel.pt
src/Products/Gloworm/browser/glowormPanelBody.pt
src/Products/Gloworm/browser/glowormPanelHeader.pt
src/Products/Gloworm/browser/glowormPanelNavTree.pt
src/Products/Gloworm/browser/inspect.css
src/Products/Gloworm/browser/inspect.kss
src/Products/Gloworm/browser/inspector.py
src/Products/Gloworm/browser/interfaces.py
src/Products/Gloworm/browser/panel_customize_viewlet.pt
src/Products/Gloworm/browser/panel_inspect_content_object.pt
src/Products/Gloworm/browser/panel_inspect_element.pt
src/Products/Gloworm/browser/panel_inspect_field.pt
src/Products/Gloworm/browser/panel_inspect_viewlet.pt
src/Products/Gloworm/browser/panel_inspect_viewlet_manager.pt
src/Products/Gloworm/browser/panel_move_viewlet.pt
src/Products/Gloworm/browser/plugin.js
src/Products/Gloworm/browser/plugin.py
src/Products/Gloworm/browser/utils.py
src/Products/Gloworm/browser/viewlets.py
src/Products/Gloworm/browser/3rd_party/__init__.py
src/Products/Gloworm/browser/3rd_party/animation-min.js
src/Products/Gloworm/browser/3rd_party/container-min.js
src/Products/Gloworm/browser/3rd_party/container.css
src/Products/Gloworm/browser/3rd_party/dragdrop-min.js
src/Products/Gloworm/browser/3rd_party/element-beta-min.js
src/Products/Gloworm/browser/3rd_party/layout-min.js
src/Products/Gloworm/browser/3rd_party/layout.css
src/Products/Gloworm/browser/3rd_party/resize-min.js
src/Products/Gloworm/browser/3rd_party/resize.css
