Metadata-Version: 1.0
Name: Products.Gloworm
Version: 1.1
Summary: A Firebug-like inspection tool for Plone
Home-page: https://weblion.psu.edu/svn/weblion/weblion/Products.Gloworm/
Author: WebLion Group, Penn State University
Author-email: support@weblion.psu.edu
License: UNKNOWN
Platform: UNKNOWN
Classifier: Framework :: Plone
Classifier: Framework :: Zope2
Classifier: Programming Language :: Python
Classifier: Programming Language :: JavaScript
Classifier: Topic :: Software Development :: Libraries :: Python Modules
Classifier: Intended Audience :: Developers
